graphstorm/__init__.py
graphstorm/gsf.py
graphstorm/utils.py
graphstorm/config/__init__.py
graphstorm/config/argument.py
graphstorm/config/config.py
graphstorm/data/__init__.py
graphstorm/data/constants.py
graphstorm/data/dataset.py
graphstorm/data/mag_lsc.py
graphstorm/data/movielens.py
graphstorm/data/ogbn_datasets.py
graphstorm/data/ogbn_mag.py
graphstorm/data/text_dataset.py
graphstorm/data/utils.py
graphstorm/dataloading/__init__.py
graphstorm/dataloading/dataloading.py
graphstorm/dataloading/dataset.py
graphstorm/dataloading/metadata.py
graphstorm/dataloading/sampler.py
graphstorm/dataloading/utils.py
graphstorm/distiller/__init__.py
graphstorm/distiller/distiller.py
graphstorm/distributed/__init__.py
graphstorm/distributed/primitives.py
graphstorm/eval/__init__.py
graphstorm/eval/eval_func.py
graphstorm/eval/evaluator.py
graphstorm/eval/utils.py
graphstorm/gconstruct/__init__.py
graphstorm/gconstruct/construct_graph.py
graphstorm/gconstruct/construct_payload_graph.py
graphstorm/gconstruct/file_io.py
graphstorm/gconstruct/id_map.py
graphstorm/gconstruct/payload_utils.py
graphstorm/gconstruct/remap_result.py
graphstorm/gconstruct/transform.py
graphstorm/gconstruct/utils.py
graphstorm/gconstruct/config_conversion/__init__.py
graphstorm/gconstruct/config_conversion/converter_base.py
graphstorm/gconstruct/config_conversion/gsprocessing_converter.py
graphstorm/gconstruct/config_conversion/meta_configuration.py
graphstorm/gpartition/__init__.py
graphstorm/gpartition/convert_to_graphbolt.py
graphstorm/gpartition/dist_partition_graph.py
graphstorm/gpartition/metis_partition.py
graphstorm/gpartition/partition_algo_base.py
graphstorm/gpartition/partition_config.py
graphstorm/gpartition/post_hard_negative.py
graphstorm/gpartition/random_partition.py
graphstorm/inference/__init__.py
graphstorm/inference/emb_infer.py
graphstorm/inference/ep_infer.py
graphstorm/inference/graphstorm_infer.py
graphstorm/inference/lp_infer.py
graphstorm/inference/mt_infer.py
graphstorm-0.5.1.dist-info/LICENSE
graphstorm-0.5.1.dist-info/METADATA
graphstorm-0.5.1.dist-info/NOTICE
graphstorm-0.5.1.dist-info/WHEEL
graphstorm-0.5.1.dist-info/top_level.txt
graphstorm-0.5.1.dist-info/zip-safe
graphstorm-0.5.1.dist-info/RECORD
