Metadata-Version: 2.1
Name: graphstorm
Version: 0.5.1
Summary: GraphStorm
Home-page: UNKNOWN
License: Apache-2.0
Platform: UNKNOWN
Requires-Python: >=3.8
License-File: LICENSE
License-File: NOTICE
Requires-Dist: h5py
Requires-Dist: pyarrow
Requires-Dist: transformers==4.48.0
Requires-Dist: pandas
Requires-Dist: scikit-learn
Requires-Dist: ogb==1.3.6
Requires-Dist: packaging
Requires-Dist: psutil
Requires-Dist: torchdata==0.9.0
Requires-Dist: pydantic
Provides-Extra: tensorboard
Requires-Dist: tensorboard>=1.15; extra == "tensorboard"
